lbranch/__init__.py
lbranch/main.py
lbranch/version.py
lbranch-0.1.4.dist-info/METADATA
lbranch-0.1.4.dist-info/WHEEL
lbranch-0.1.4.dist-info/entry_points.txt
lbranch-0.1.4.dist-info/licenses/LICENSE
lbranch-0.1.4.dist-info/RECORD
