Metadata-Version: 2.4
Name: lbranch
Version: 0.1.4
Summary: A Git utility that shows recently checked-out branches in chronological order and lets you quickly switch between them.
Project-URL: Homepage, https://github.com/dcchuck/lbranch
Project-URL: Source Code, https://github.com/dcchuck/lbranch
Author: Chuck Danielsson
License-Expression: MIT
License-File: LICENSE
Keywords: branch,cli,developer-tools,git,git-tools,version-control
Classifier: Development Status :: 4 - Beta
Classifier: Environment :: Console
Classifier: Intended Audience :: Developers
Classifier: License :: OSI Approved :: MIT License
Classifier: Natural Language :: English
Classifier: Programming Language :: Python :: 3
Classifier: Programming Language :: Python :: 3.7
Classifier: Programming Language :: Python :: 3.8
Classifier: Programming Language :: Python :: 3.9
Classifier: Programming Language :: Python :: 3.10
Classifier: Programming Language :: Python :: 3.11
Classifier: Topic :: Software Development :: Version Control :: Git
Classifier: Topic :: Utilities
Requires-Python: >=3.7
